ecmind_blue_client_portfolio/__init__.py
ecmind_blue_client_portfolio/portfolio.py
ecmind_blue_client_portfolio-0.0.3.dist-info/LICENSE
ecmind_blue_client_portfolio-0.0.3.dist-info/METADATA
ecmind_blue_client_portfolio-0.0.3.dist-info/WHEEL
ecmind_blue_client_portfolio-0.0.3.dist-info/top_level.txt
ecmind_blue_client_portfolio-0.0.3.dist-info/RECORD
