Metadata-Version: 2.1
Name: ecmind-blue-client-portfolio
Version: 0.0.3
Summary: Helper modules for the ecmind_blue_client to ease the work with the portfolio API functions.
Home-page: https://gitlab.ecmind.ch/open/ecmind_blue_client_portfolio
Author: Roland Koller
Author-email: info@ecmind.ch
License: UNKNOWN
Platform: UNKNOWN
Classifier: Programming Language :: Python :: 3
Classifier: License :: OSI Approved :: MIT License
Classifier: Operating System :: OS Independent
Requires-Python: >=3.9
License-File: LICENSE
Requires-Dist: ecmind-blue-client (>=0.4.0)
Requires-Dist: XmlElement (>=0.3.1)
